{
  "manual_weights": {
    "structural": 0.3,
    "emergency_capacity": 0.25,
    "lifeline_robustness": 0.25,
    "accessibility": 0.2
  },
  "entropy_weights": {
    "structural": 0.0728,
    "emergency_capacity": 0.0,
    "lifeline_robustness": 0.2759,
    "accessibility": 0.6513
  },
  "entropy_hybrid_weights": {
    "structural": 0.0582,
    "emergency_capacity": 0.2,
    "lifeline_robustness": 0.2207,
    "accessibility": 0.521
  },
  "citywide_eri_manual": 70.9,
  "citywide_eri_entropy": 73.7,
  "citywide_eri_entropy_hybrid": 76.1,
  "delta_points_manual_vs_hybrid": 5.2
}